scordt/__init__.py
scordt/arc2.py
scordt/func.py
scordt/plots.py
scordt/reads.py
scordt/setup_cython.py
scordt/slicesPlot.py
scordt/test_csv.py
scordt-0.1.1.dist-info/LICENSE
scordt-0.1.1.dist-info/METADATA
scordt-0.1.1.dist-info/WHEEL
scordt-0.1.1.dist-info/top_level.txt
scordt-0.1.1.dist-info/RECORD
